tox_wikimedia/__init__.py
tox_wikimedia-0.0.4.dist-info/COPYING
tox_wikimedia-0.0.4.dist-info/METADATA
tox_wikimedia-0.0.4.dist-info/WHEEL
tox_wikimedia-0.0.4.dist-info/entry_points.txt
tox_wikimedia-0.0.4.dist-info/top_level.txt
tox_wikimedia-0.0.4.dist-info/RECORD
