Metadata-Version: 2.1
Name: tox-wikimedia
Version: 0.0.4
Summary: Automatically configure tox environments to use Wikimedia's standard tools
Home-page: https://www.mediawiki.org/wiki/tox-wikimedia
Author: Kunal Mehta
Author-email: legoktm@debian.org
Classifier: Development Status :: 4 - Beta
Classifier: Intended Audience :: Developers
Classifier: Framework :: tox
Classifier: License :: OSI Approved :: GNU General Public License v3 or later (GPLv3+)
Classifier: Programming Language :: Python :: 3.7
Classifier: Programming Language :: Python :: 3.8
Classifier: Programming Language :: Python :: 3.9
Classifier: Programming Language :: Python :: 3.10
License-File: COPYING
Requires-Dist: tox (<4,>=3.8.0)
